echo_kernel/__init__.py
echo_kernel/__main__.py
echo_kernel/install.py
echo_kernel/kernel.py
echo_kernel-1.1.dist-info/DESCRIPTION.rst
echo_kernel-1.1.dist-info/METADATA
echo_kernel-1.1.dist-info/RECORD
echo_kernel-1.1.dist-info/WHEEL
echo_kernel-1.1.dist-info/metadata.json
echo_kernel-1.1.dist-info/top_level.txt
