Metadata-Version: 2.0
Name: echo-kernel
Version: 1.1
Summary: Simple example kernel for Jupyter
Home-page: https://github.com/jupyter/echo_kernel
Author: Jupyter Development Team
Author-email: jupyter@googlegroups.com
License: UNKNOWN
Platform: UNKNOWN
Classifier: Intended Audience :: Developers
Classifier: License :: OSI Approved :: BSD License
Classifier: Programming Language :: Python :: 3
